[
  {
    "inputs": [],
    "name": "BothPlayersNotStaked",
    "type": "error"
  },
  {
    "inputs": [],
    "name": "InvalidMatchId",
    "type": "error"
  },
  {
    "inputs": [],
    "name": "InvalidPlayer",
    "type": "error"
  },
  {
    "inputs": [],
    "name": "InvalidStakeAmount",
    "type": "error"
  },
  {
    "inputs": [],
    "name": "InvalidWinner",
    "type": "error"
  },
  {
    "inputs": [],
    "name": "MatchAlreadyCompleted",
    "type": "error"
  },
  {
    "inputs": [],
    "name": "MatchAlreadyExists",
    "type": "error"
  },
  {
    "inputs": [],
    "name": "MatchNotFound",
    "type": "error"
  },
  {
    "inputs": [],
    "name": "UnauthorizedCaller",
    "type": "error"
  },
  {
    "inputs": [],
    "name": "ZeroAddress",
    "type": "error"
  },
  {
    "anonymous": false,
    "inputs": [
      {
        "indexed": true,
        "internalType": "bytes32",
        "name": "matchId",
        "type": "bytes32"
      },
      {
        "indexed": true,
        "internalType": "address",
        "name": "player1",
        "type": "address"
      },
      {
        "indexed": true,
        "internalType": "address",
        "name": "player2",
        "type": "address"
      },
      {
        "indexed": false,
        "internalType": "uint256",
        "name": "refundAmount",
        "type": "uint256"
      }
    ],
    "name": "MatchCancelled",
    "type": "event"
  },
  {
    "anonymous": false,
    "inputs": [
      {
        "indexed": true,
        "internalType": "bytes32",
        "name": "matchId",
        "type": "bytes32"
      },
      {
        "indexed": true,
        "internalType": "address",
        "name": "winner",
        "type": "address"
      },
      {
        "indexed": false,
        "internalType": "uint256",
        "name": "winnerPayout",
        "type": "uint256"
      },
      {
        "indexed": false,
        "internalType": "uint256",
        "name": "platformFee",
        "type": "uint256"
      }
    ],
    "name": "MatchCompleted",
    "type": "event"
  },
  {
    "anonymous": false,
    "inputs": [
      {
        "indexed": true,
        "internalType": "bytes32",
        "name": "matchId",
        "type": "bytes32"
      },
      {
        "indexed": true,
        "internalType": "address",
        "name": "player1",
        "type": "address"
      },
      {
        "indexed": true,
        "internalType": "address",
        "name": "player2",
        "type": "address"
      },
      {
        "indexed": false,
        "internalType": "uint256",
        "name": "stakeAmount",
        "type": "uint256"
      }
    ],
    "name": "MatchCreated",
    "type": "event"
  },
  {
    "anonymous": false,
    "inputs": [
      {
        "indexed": true,
        "internalType": "bytes32",
        "name": "matchId",
        "type": "bytes32"
      },
      {
        "indexed": true,
        "internalType": "address",
        "name": "player1",
        "type": "address"
      },
      {
        "indexed": true,
        "internalType": "address",
        "name": "player2",
        "type": "address"
      },
      {
        "indexed": false,
        "internalType": "uint256",
        "name": "payoutEach",
        "type": "uint256"
      }
    ],
    "name": "PotSplit",
    "type": "event"
  },
  {
    "anonymous": false,
    "inputs": [
      {
        "indexed": true,
        "internalType": "bytes32",
        "name": "matchId",
        "type": "bytes32"
      },
      {
        "indexed": true,
        "internalType": "address",
        "name": "player",
        "type": "address"
      },
      {
        "indexed": false,
        "internalType": "uint256",
        "name": "amount",
        "type": "uint256"
      }
    ],
    "name": "StakeDeposited",
    "type": "event"
  },
  {
    "inputs": [],
    "name": "accumulatedFees",
    "outputs": [
      {
        "internalType": "uint256",
        "name": "",
        "type": "uint256"
      }
    ],
    "stateMutability": "view",
    "type": "function"
  },
  {
    "inputs": [],
    "name": "backend",
    "outputs": [
      {
        "internalType": "address",
        "name": "",
        "type": "address"
      }
    ],
    "stateMutability": "view",
    "type": "function"
  },
  {
    "inputs": [
      {
        "internalType": "bytes32",
        "name": "matchId",
        "type": "bytes32"
      }
    ],
    "name": "cancelMatch",
    "outputs": [],
    "stateMutability": "nonpayable",
    "type": "function"
  },
  {
    "inputs": [
      {
        "internalType": "bytes32",
        "name": "matchId",
        "type": "bytes32"
      },
      {
        "internalType": "address",
        "name": "winner",
        "type": "address"
      }
    ],
    "name": "completeMatch",
    "outputs": [],
    "stateMutability": "nonpayable",
    "type": "function"
  },
  {
    "inputs": [
      {
        "internalType": "bytes32",
        "name": "matchId",
        "type": "bytes32"
      },
      {
        "internalType": "address",
        "name": "player1",
        "type": "address"
      },
      {
        "internalType": "address",
        "name": "player2",
        "type": "address"
      },
      {
        "internalType": "uint256",
        "name": "stakeAmount",
        "type": "uint256"
      }
    ],
    "name": "createMatch",
    "outputs": [],
    "stateMutability": "nonpayable",
    "type": "function"
  },
  {
    "inputs": [
      {
        "internalType": "bytes32",
        "name": "matchId",
        "type": "bytes32"
      }
    ],
    "name": "depositStake",
    "outputs": [],
    "stateMutability": "nonpayable",
    "type": "function"
  },
  {
    "inputs": [
      {
        "internalType": "bytes32",
        "name": "matchId",
        "type": "bytes32"
      }
    ],
    "name": "getMatch",
    "outputs": [
      {
        "components": [
          {
            "internalType": "address",
            "name": "player1",
            "type": "address"
          },
          {
            "internalType": "address",
            "name": "player2",
            "type": "address"
          },
          {
            "internalType": "uint256",
            "name": "stakeAmount",
            "type": "uint256"
          },
          {
            "internalType": "bool",
            "name": "player1Staked",
            "type": "bool"
          },
          {
            "internalType": "bool",
            "name": "player2Staked",
            "type": "bool"
          },
          {
            "internalType": "bool",
            "name": "completed",
            "type": "bool"
          },
          {
            "internalType": "bool",
            "name": "cancelled",
            "type": "bool"
          }
        ],
        "internalType": "struct BlinkBattleEscrow.Match",
        "name": "",
        "type": "tuple"
      }
    ],
    "stateMutability": "view",
    "type": "function"
  },
  {
    "inputs": [
      {
        "internalType": "bytes32",
        "name": "matchId",
        "type": "bytes32"
      }
    ],
    "name": "isMatchReady",
    "outputs": [
      {
        "internalType": "bool",
        "name": "",
        "type": "bool"
      }
    ],
    "stateMutability": "view",
    "type": "function"
  },
  {
    "inputs": [
      {
        "internalType": "bytes32",
        "name": "",
        "type": "bytes32"
      }
    ],
    "name": "matches",
    "outputs": [
      {
        "internalType": "address",
        "name": "player1",
        "type": "address"
      },
      {
        "internalType": "address",
        "name": "player2",
        "type": "address"
      },
      {
        "internalType": "uint256",
        "name": "stakeAmount",
        "type": "uint256"
      },
      {
        "internalType": "bool",
        "name": "player1Staked",
        "type": "bool"
      },
      {
        "internalType": "bool",
        "name": "player2Staked",
        "type": "bool"
      },
      {
        "internalType": "bool",
        "name": "completed",
        "type": "bool"
      },
      {
        "internalType": "bool",
        "name": "cancelled",
        "type": "bool"
      }
    ],
    "stateMutability": "view",
    "type": "function"
  },
  {
    "inputs": [],
    "name": "platformWallet",
    "outputs": [
      {
        "internalType": "address",
        "name": "",
        "type": "address"
      }
    ],
    "stateMutability": "view",
    "type": "function"
  },
  {
    "inputs": [
      {
        "internalType": "bytes32",
        "name": "matchId",
        "type": "bytes32"
      }
    ],
    "name": "splitPot",
    "outputs": [],
    "stateMutability": "nonpayable",
    "type": "function"
  },
  {
    "inputs": [],
    "name": "wldToken",
    "outputs": [
      {
        "internalType": "contract IERC20",
        "name": "",
        "type": "address"
      }
    ],
    "stateMutability": "view",
    "type": "function"
  },
  {
    "inputs": [],
    "name": "withdrawFees",
    "outputs": [],
    "stateMutability": "nonpayable",
    "type": "function"
  }
]
